{
    "title": "Cookie Collective Twitch Stream #2",
    "started": "2020-03-26",
    "date": "26 March 2020",
    "type": "Live Performance",
    "vod": "https://www.twitch.tv/videos/576039130",
    "software_used": [
        {
            "name": "Bonzomatic",
            "url": "https://github.com/TheNuSan/Bonzomatic/releases/tag/v09",
            "version": "NuSan - v09",
            "purpose": "Graphic"
        },
        {
            "name": "TidalCycles",
            "url": "https://tidalcycles.org/",
            "version": "",
            "purpose": "Music"
        }
    ],
    "phases": [
        {
            "title": "",
            "vod": null,
            "entries": [
                {
                    "id": null,
                    "rank": null,
                    "points": null,
                    "handle": {
                        "name": "alkama",
                        "demozoo_id": 1382
                    },
                    "shadertoy_url": null,
                    "preview_image": "2020_03_26_shader_showdown_paris_cc_streaming_2/alkama.jpg",
                    "source_file": "https://github.com/CookieCollective/Live-Coding-Sources/blob/master/2020-03-26/alkama.glsl"
                },
                {
                    "id": null,
                    "rank": null,
                    "points": null,
                    "handle": {
                        "name": "Anton",
                        "demozoo_id": null
                    },
                    "shadertoy_url": null,
                    "preview_image": "2020_03_26_shader_showdown_paris_cc_streaming_2/anton.jpg",
                    "source_file": "https://github.com/CookieCollective/Live-Coding-Sources/blob/master/2020-03-26/anton.glsl"
                },
                {
                    "id": null,
                    "rank": null,
                    "points": null,
                    "handle": {
                        "name": "bruce",
                        "demozoo_id": null
                    },
                    "shadertoy_url": null,
                    "preview_image": "2020_03_26_shader_showdown_paris_cc_streaming_2/bruce.jpg",
                    "source_file": "https://github.com/CookieCollective/Live-Coding-Sources/blob/master/2020-03-26/bruce.glsl"
                },
                {
                    "id": null,
                    "rank": null,
                    "points": null,
                    "handle": {
                        "name": "cookie",
                        "demozoo_id": null
                    },
                    "shadertoy_url": null,
                    "preview_image": "2020_03_26_shader_showdown_paris_cc_streaming_2/cookie.jpg",
                    "source_file": "https://github.com/CookieCollective/Live-Coding-Sources/blob/master/2020-03-26/cookie.glsl"
                },
                {
                    "id": null,
                    "rank": null,
                    "points": null,
                    "handle": {
                        "name": "Flopine",
                        "demozoo_id": 65988
                    },
                    "shadertoy_url": null,
                    "preview_image": "2020_03_26_shader_showdown_paris_cc_streaming_2/flopine.jpg",
                    "source_file": "https://github.com/CookieCollective/Live-Coding-Sources/blob/master/2020-03-26/flopine.glsl"
                },
                {
                    "id": null,
                    "rank": null,
                    "points": null,
                    "handle": {
                        "name": "lamogui",
                        "demozoo_id": 71129
                    },
                    "shadertoy_url": null,
                    "preview_image": "2020_03_26_shader_showdown_paris_cc_streaming_2/lamogui.jpg",
                    "source_file": "https://github.com/CookieCollective/Live-Coding-Sources/blob/master/2020-03-26/lamogui.glsl"
                },
                {
                    "id": null,
                    "rank": null,
                    "points": null,
                    "handle": {
                        "name": "NuSan",
                        "demozoo_id": 88839
                    },
                    "shadertoy_url": null,
                    "preview_image": "2020_03_26_shader_showdown_paris_cc_streaming_2/nusan.jpg",
                    "source_file": "https://github.com/CookieCollective/Live-Coding-Sources/blob/master/2020-03-26/nusan.glsl"
                },
                {
                    "id": null,
                    "rank": null,
                    "points": null,
                    "handle": {
                        "name": "ponk",
                        "demozoo_id": 61858
                    },
                    "shadertoy_url": null,
                    "preview_image": "2020_03_26_shader_showdown_paris_cc_streaming_2/ponk.jpg",
                    "source_file": "https://github.com/CookieCollective/Live-Coding-Sources/blob/master/2020-03-26/ponk.glsl"
                },
                {
                    "id": null,
                    "rank": null,
                    "points": null,
                    "handle": {
                        "name": "wrighter",
                        "demozoo_id": 113559
                    },
                    "shadertoy_url": null,
                    "preview_image": "2020_03_26_shader_showdown_paris_cc_streaming_2/Wrighter.jpg",
                    "source_file": "https://github.com/CookieCollective/Live-Coding-Sources/blob/master/2020-03-26/Wrighter.glsl"
                }
            ],
            "staffs": []
        }
    ],
    "staffs": [
        {
            "handle": {
                "name": "Cookie Collective",
                "demozoo_id": 78435
            },
            "job": "Organizers"
        }
    ],
    "demozoo_party_id": "LCDZCOOKIE"
}
